at_address_compare-0.3.0.dist-info/DESCRIPTION.rst
at_address_compare-0.3.0.dist-info/METADATA
at_address_compare-0.3.0.dist-info/RECORD
at_address_compare-0.3.0.dist-info/WHEEL
at_address_compare-0.3.0.dist-info/entry_points.txt
at_address_compare-0.3.0.dist-info/metadata.json
at_address_compare-0.3.0.dist-info/top_level.txt
ataddrcompare/__init__.py
ataddrcompare/__main__.py
ataddrcompare/ataddrcompare.py
ataddrcompare/template.html
ataddrcompare/template.txt
