Metadata-Version: 2.0
Name: at-address-compare
Version: 0.3.0
Summary: Address comparison of OSM data with official open data for Austria.
Home-page: https://github.com/gmgeo/at-address-compare
Author: Michael Glanznig
Author-email: UNKNOWN
License: MIT
Download-URL: https://github.com/gmgeo/at-address-compare/tarball/0.3.0
Keywords: Austria,OSM,OpenStreetMap,OpenData,addresses,address,compare
Platform: UNKNOWN
Requires-Dist: overpass
